standard_open_inflation_package/__init__.py
standard_open_inflation_package/browser.py
standard_open_inflation_package/browser_engines.py
standard_open_inflation_package/content_loader.py
standard_open_inflation_package/direct_request_interceptor.py
standard_open_inflation_package/exceptions.py
standard_open_inflation_package/handler.py
standard_open_inflation_package/inject_fetch.js
standard_open_inflation_package/models.py
standard_open_inflation_package/page.py
standard_open_inflation_package/tools.py
standard_open_inflation_package/config/__init__.py
standard_open_inflation_package/config/errors.py
standard_open_inflation_package/config/logs.py
standard_open_inflation_package/config/network.py
standard_open_inflation_package/config/parameters.py
standard_open_inflation_package/utils/docs_generator.py
standard_open_inflation_package-0.1.7.1.dist-info/licenses/LICENSE
tests/docs_generator_test.py
tests/parsers_test.py
tests/tools_test.py
tests/api/__init__.py
tests/api/base_request_tests.py
tests/api/cookie_tests.py
tests/api/interceptor_tests.py
tests/api/json_and_headers_tests.py
tests/browser/test_engine_init.py
standard_open_inflation_package-0.1.7.1.dist-info/METADATA
standard_open_inflation_package-0.1.7.1.dist-info/WHEEL
standard_open_inflation_package-0.1.7.1.dist-info/entry_points.txt
standard_open_inflation_package-0.1.7.1.dist-info/top_level.txt
standard_open_inflation_package-0.1.7.1.dist-info/RECORD
