Metadata-Version: 2.4
Name: standard_open_inflation_package
Version: 0.1.7.1
Summary: Standard Open Inflation Package for all API's
Author: Miskler
License: MIT
Project-URL: Homepage, https://github.com/Open-Inflation/standard_open_inflation_package
Classifier: Programming Language :: Python :: 3
Classifier: Programming Language :: Python :: 3.10
Classifier: Programming Language :: Python :: 3.11
Classifier: Programming Language :: Python :: 3.12
Classifier: Programming Language :: Python :: 3.13
Classifier: License :: OSI Approved :: MIT License
Classifier: Operating System :: Microsoft :: Windows
Classifier: Operating System :: POSIX :: Linux
Classifier: Intended Audience :: Developers
Classifier: Intended Audience :: Information Technology
Classifier: Topic :: Software Development :: Libraries :: Python Modules
Classifier: Topic :: Internet
Classifier: Topic :: Utilities
Requires-Python: >=3.10
License-File: LICENSE
Requires-Dist: playwright
Requires-Dist: beartype
Provides-Extra: camoufox
Requires-Dist: camoufox[geoip]; extra == "camoufox"
Provides-Extra: test
Requires-Dist: pytest; extra == "test"
Requires-Dist: pytest-asyncio; extra == "test"
Requires-Dist: pytest-xdist; extra == "test"
Dynamic: license-file
